curriculum_module_generator/__init__.py
curriculum_module_generator/block.py
curriculum_module_generator/block_factory.py
curriculum_module_generator/cell_type.py
curriculum_module_generator/content_generator.py
curriculum_module_generator/main.py
curriculum_module_generator/template_generator.py
curriculum_module_generator-0.0.1.dist-info/LICENSE
curriculum_module_generator-0.0.1.dist-info/METADATA
curriculum_module_generator-0.0.1.dist-info/WHEEL
curriculum_module_generator-0.0.1.dist-info/entry_points.txt
curriculum_module_generator-0.0.1.dist-info/top_level.txt
curriculum_module_generator-0.0.1.dist-info/RECORD
